jackdaw_ml/__init__.py
jackdaw_ml/access_interface/__init__.py
jackdaw_ml/access_interface/dict_interface.py
jackdaw_ml/access_interface/list_interface.py
jackdaw_ml/artefact_container.py
jackdaw_ml/artefact_decorator.py
jackdaw_ml/artefact_dict.py
jackdaw_ml/artefact_endpoint.py
jackdaw_ml/base_architecture.py
jackdaw_ml/child_architecture.py
jackdaw_ml/config_loader.py
jackdaw_ml/debugging.py
jackdaw_ml/detectors/__init__.py
jackdaw_ml/detectors/child_architecture_detector.py
jackdaw_ml/detectors/class_detector.py
jackdaw_ml/detectors/hook.py
jackdaw_ml/detectors/keras.py
jackdaw_ml/detectors/lightgbm.py
jackdaw_ml/detectors/sklearn.py
jackdaw_ml/detectors/torch.py
jackdaw_ml/entrypoint_architecture.py
jackdaw_ml/loads.py
jackdaw_ml/metric_logging.py
jackdaw_ml/resource.py
jackdaw_ml/run_id.py
jackdaw_ml/saves.py
jackdaw_ml/search/__init__.py
jackdaw_ml/serializers/__init__.py
jackdaw_ml/serializers/keras.py
jackdaw_ml/serializers/pickle.py
jackdaw_ml/serializers/tensor.py
jackdaw_ml/trace.py
jackdaw_ml/vcs.py
jackdaw_ml-0.0.7.dist-info/METADATA
jackdaw_ml-0.0.7.dist-info/WHEEL
jackdaw_ml-0.0.7.dist-info/LICENSE
jackdaw_ml-0.0.7.dist-info/RECORD
