Metadata-Version: 2.1
Name: jackdaw-ml
Version: 0.0.7
Summary: Share and Organise Machine Learning Models
License: LGPL-3.0-or-later
Author: Lissa Hyacinth
Author-email: lissa@shareableai.com
Requires-Python: >=3.10,<3.12
Classifier: License :: OSI Approved :: GNU Lesser General Public License v3 or later (LGPLv3+)
Classifier: Programming Language :: Python :: 3
Classifier: Programming Language :: Python :: 3.10
Classifier: Programming Language :: Python :: 3.11
Requires-Dist: artefactlink (>=0.4.1)
Requires-Dist: gitpython (>=3,<4)
Requires-Dist: giturlparse (>=0,<1)
Requires-Dist: pyarrow (>=9,<10)
Requires-Dist: urllib3 (>=1,<2)
